<?xml version="1.0" encoding="UTF-8"?>
<!-- Generated by JClic - https://projectestac.github.io/jclic -->
<manifest identifier="JClic-1CC888" version="1.0" xmlns="http://www.imsproject.org/xsd/imscp_rootv1p1p2" xmlns:adlcp="http://www.adlnet.org/xsd/adlcp_rootv1p2" xmlns:xsi="http://www.w3.org/2001/XMLSchema-instance" xsi:schemaLocation= "http://www.imsproject.org/xsd/imscp_rootv1p1p2 imscp_rootv1p1p2.xsd http://www.imsglobal.org/xsd/imsmd_rootv1p2p1 imsmd_rootv1p2p1.xsd http://www.adlnet.org/xsd/adlcp_rootv1p2 adlcp_rootv1p2.xsd">
 <metadata> 
  <schema>ADL SCORM</schema>
  <schemaversion>1.2</schemaversion>
 </metadata> 
 <organizations default="JClic">  
  <organization identifier="JClic">  
   <title>Geomorfología</title>
   <item identifier="ITEM_JClic-1CC888" identifierref="RES_JClic-1CC888">
    <title>Geomorfología</title>
   </item>
  </organization>
 </organizations>
 <resources>
  <resource identifier="RES_JClic-1CC888" type="webcontent" href="/index.html" adlcp:scormtype="sco"> 
   <file href="0002n002.jpg"/>
   <file href="0002n009.jpg"/>
   <file href="146607-150x500.jpg"/>
   <file href="1copy.gif"/>
   <file href="265.gif"/>
   <file href="_destructivo_a.jpg"/>
   <file href="_destructivo_b.jpg"/>
   <file href="_placas.jpg"/>
   <file href="_relieve.jpg"/>
   <file href="bonne.jpg"/>
   <file href="bordes1.jpg"/>
   <file href="bordes2.jpg"/>
   <file href="canarias_origen.gif"/>
   <file href="cluseb.gif"/>
   <file href="combeb.gif"/>
   <file href="conten2.jpg"/>
   <file href="deriva.gif"/>
   <file href="earth_cutbkb.gif"/>
   <file href="erupcion.jpg"/>
   <file href="erupcion1_nt.jpg"/>
   <file href="erupcion_p.jpg"/>
   <file href="erupciones.gif"/>
   <file href="favicon.ico"/>
   <file href="geol_geodinint_partesvolcanb.gif"/>
   <file href="geomorf.jpg"/>
   <file href="geomorfo.jclic"/>
   <file href="geomorfo.jclic.js"/>
   <file href="horst.gif"/>
   <file href="horstb.gif"/>
   <file href="icon-192.png"/>
   <file href="icon-72.png"/>
   <file href="image220_1.jpg"/>
   <file href="imsmanifest.xml"/>
   <file href="index.html"/>
   <file href="j0385783.jpg"/>
   <file href="manto.gif"/>
   <file href="mantob.gif"/>
   <file href="mapa.jpg"/>
   <file href="partefalla.gif"/>
   <file href="partefallab.gif"/>
   <file href="plegamientos.jpg"/>
   <file href="pliegue22.gif"/>
   <file href="pliegue2b.gif"/>
   <file href="plitip.gif"/>
   <file href="plitipb.gif"/>
   <file href="popo.jpg"/>
   <file href="project-cover.jpg"/>
   <file href="project-thumb.jpg"/>
   <file href="project.json"/>
   <file href="psdiag.jpg"/>
   <file href="reliev3.jpg"/>
   <file href="reliev4.jpg"/>
   <file href="ruzb.gif"/>
   <file href="sandsheet.jpg"/>
   <file href="terremoto.gif"/>
   <file href="terremotos.gif"/>
   <file href="tiposfalla.gif"/>
   <file href="tiposfallab.gif"/>
  </resource>
 </resources>
</manifest>