<?xml version="1.0" encoding="UTF-8"?>
<!-- Generated by JClic - https://projectestac.github.io/jclic -->
<manifest identifier="JClic-BA851A" version="1.0" xmlns="http://www.imsproject.org/xsd/imscp_rootv1p1p2" xmlns:adlcp="http://www.adlnet.org/xsd/adlcp_rootv1p2" xmlns:xsi="http://www.w3.org/2001/XMLSchema-instance" xsi:schemaLocation= "http://www.imsproject.org/xsd/imscp_rootv1p1p2 imscp_rootv1p1p2.xsd http://www.imsglobal.org/xsd/imsmd_rootv1p2p1 imsmd_rootv1p2p1.xsd http://www.adlnet.org/xsd/adlcp_rootv1p2 adlcp_rootv1p2.xsd">
 <metadata> 
  <schema>ADL SCORM</schema>
  <schemaversion>1.2</schemaversion>
 </metadata> 
 <organizations default="JClic">  
  <organization identifier="JClic">  
   <title>Aprendiendo a reciclar</title>
   <item identifier="ITEM_JClic-BA851A" identifierref="RES_JClic-BA851A">
    <title>Aprendiendo a reciclar</title>
   </item>
  </organization>
 </organizations>
 <resources>
  <resource identifier="RES_JClic-BA851A" type="webcontent" href="/index.html" adlcp:scormtype="sco"> 
   <file href="3contene.gif"/>
   <file href="actmel.gif"/>
   <file href="agua.gif"/>
   <file href="amarillo.gif"/>
   <file href="autob2.gif"/>
   <file href="azul3.gif"/>
   <file href="bote.gif"/>
   <file href="botelas2.gif"/>
   <file href="botella2.gif"/>
   <file href="caja2.gif"/>
   <file href="cajas2.gif"/>
   <file href="campo2.gif"/>
   <file href="cocacol.gif"/>
   <file href="colacao.gif"/>
   <file href="cristal2.gif"/>
   <file href="estupend.wav"/>
   <file href="favicon.ico"/>
   <file href="galleta.gif"/>
   <file href="garrafa2.gif"/>
   <file href="genial.wav"/>
   <file href="icon-192.png"/>
   <file href="icon-72.png"/>
   <file href="imsmanifest.xml"/>
   <file href="index.html"/>
   <file href="jabon2.gif"/>
   <file href="leche.gif"/>
   <file href="libros2.gif"/>
   <file href="manteq.gif"/>
   <file href="muybien.wav"/>
   <file href="pancar2.gif"/>
   <file href="papeles.gif"/>
   <file href="periodic.gif"/>
   <file href="portada.gif"/>
   <file href="project-cover.jpg"/>
   <file href="project-thumb.jpg"/>
   <file href="project.json"/>
   <file href="recicla3.jclic"/>
   <file href="recicla3.jclic.js"/>
   <file href="ruidos2.gif"/>
   <file href="ruidos3.gif"/>
   <file href="sonidfin.wav"/>
   <file href="verde2.gif"/>
   <file href="yogur.gif"/>
  </resource>
 </resources>
</manifest>