<?xml version="1.0" encoding="UTF-8"?>
<!-- Generated by JClic - https://projectestac.github.io/jclic -->
<manifest identifier="JClic-EB9F7A" version="1.0" xmlns="http://www.imsproject.org/xsd/imscp_rootv1p1p2" xmlns:adlcp="http://www.adlnet.org/xsd/adlcp_rootv1p2" xmlns:xsi="http://www.w3.org/2001/XMLSchema-instance" xsi:schemaLocation= "http://www.imsproject.org/xsd/imscp_rootv1p1p2 imscp_rootv1p1p2.xsd http://www.imsglobal.org/xsd/imsmd_rootv1p2p1 imsmd_rootv1p2p1.xsd http://www.adlnet.org/xsd/adlcp_rootv1p2 adlcp_rootv1p2.xsd">
 <metadata> 
  <schema>ADL SCORM</schema>
  <schemaversion>1.2</schemaversion>
 </metadata> 
 <organizations default="JClic">  
  <organization identifier="JClic">  
   <title>Los alimentos</title>
   <item identifier="ITEM_JClic-EB9F7A" identifierref="RES_JClic-EB9F7A">
    <title>Los alimentos</title>
   </item>
  </organization>
 </organizations>
 <resources>
  <resource identifier="RES_JClic-EB9F7A" type="webcontent" href="/index.html" adlcp:scormtype="sco"> 
   <file href="aliment.jclic"/>
   <file href="aliment.jclic.js"/>
   <file href="bocadil.gif"/>
   <file href="bocadillo.wav"/>
   <file href="cerezas.gif"/>
   <file href="cerezas.wav"/>
   <file href="chul.gif"/>
   <file href="comida.gif"/>
   <file href="estupendo.wav"/>
   <file href="favicon.ico"/>
   <file href="fresa.gif"/>
   <file href="fruteria.gif"/>
   <file href="frutero.gif"/>
   <file href="hortaliz.gif"/>
   <file href="huevos.gif"/>
   <file href="icon-192.png"/>
   <file href="icon-72.png"/>
   <file href="imsmanifest.xml"/>
   <file href="index.html"/>
   <file href="inthes.mid"/>
   <file href="kiwis.gif"/>
   <file href="leche.gif"/>
   <file href="manzana.gif"/>
   <file href="mensaje.wav"/>
   <file href="mission.mid"/>
   <file href="muyb.wav"/>
   <file href="muybien.wav"/>
   <file href="naranja.gif"/>
   <file href="naranja.wav"/>
   <file href="pan.gif"/>
   <file href="pan.wav"/>
   <file href="pera2.gif"/>
   <file href="pi_a.gif"/>
   <file href="platano.gif"/>
   <file href="platano2.gif"/>
   <file href="pollo.gif"/>
   <file href="portada2.gif"/>
   <file href="project-cover.jpg"/>
   <file href="project-thumb.jpg"/>
   <file href="project.json"/>
   <file href="queso.gif"/>
   <file href="queso.wav"/>
   <file href="sandia.gif"/>
   <file href="tomate.gif"/>
   <file href="tomate.wav"/>
   <file href="uva.gif"/>
   <file href="uva.wav"/>
   <file href="yogur.gif"/>
   <file href="yogur.wav"/>
   <file href="zanahori.gif"/>
  </resource>
 </resources>
</manifest>